<annotation verified="yes">
    <folder>Annotation</folder>
    <filename>bottle_v3_613.jpg</filename>
    <path>Bottle_V3-PascalVOC-export/Annotations/bottle_v3_613.jpg</path>
    <source>
        <database>Unknown</database>
    </source>
    <size>
        <width>224</width>
        <height>224</height>
        <depth>3</depth>
    </size>
    <segmented>0</segmented>
    <object>
    <name>bottle</name>
    <pose>Unspecified</pose>
    <truncated>0</truncated>
    <difficult>0</difficult>
    <bndbox>
        <xmin>51.69230769230769</xmin>
        <ymin>14.190045248868778</ymin>
        <xmax>116.56108597285068</xmax>
        <ymax>207.78280542986425</ymax>
    </bndbox>
</object>
</annotation>
